{
  "symbol": "6J",
  "code": "097741",
  "name": "Japanese Yen",
  "market_name": "JAPANESE YEN - CHICAGO MERCANTILE EXCHANGE",
  "latest": {
    "week": "2026-05-12",
    "open_interest": 362042,
    "comm_long": 203023,
    "comm_short": 128880,
    "comm_net": 74143,
    "noncomm_long": 100155,
    "noncomm_short": 175257,
    "noncomm_net": -75102,
    "nonrept_net": 959
  },
  "comm_net_stats": {
    "percentile_5y": 51.0,
    "zscore_5y": 0.35,
    "min_5y": -201897,
    "max_5y": 194545,
    "mean_5y": 43857.0
  },
  "noncomm_net_stats": {
    "percentile_5y": 35.6,
    "zscore_5y": -0.46,
    "min_5y": -184223,
    "max_5y": 179212,
    "mean_5y": -39178.0
  },
  "signal": "neutral",
  "history": [
    {
      "week": "2021-05-25",
      "open_interest": 153196,
      "comm_long": 107377,
      "comm_short": 46024,
      "comm_net": 61353,
      "noncomm_long": 24163,
      "noncomm_short": 74319,
      "noncomm_net": -50156,
      "nonrept_net": -11197
    },
    {
      "week": "2021-06-01",
      "open_interest": 162091,
      "comm_long": 110690,
      "comm_short": 48111,
      "comm_net": 62579,
      "noncomm_long": 29462,
      "noncomm_short": 76577,
      "noncomm_net": -47115,
      "nonrept_net": -15464
    },
    {
      "week": "2021-06-08",
      "open_interest": 161592,
      "comm_long": 108879,
      "comm_short": 54611,
      "comm_net": 54268,
      "noncomm_long": 27248,
      "noncomm_short": 64562,
      "noncomm_net": -37314,
      "nonrept_net": -16954
    },
    {
      "week": "2021-06-15",
      "open_interest": 155359,
      "comm_long": 112798,
      "comm_short": 47481,
      "comm_net": 65317,
      "noncomm_long": 22974,
      "noncomm_short": 69824,
      "noncomm_net": -46850,
      "nonrept_net": -18467
    },
    {
      "week": "2021-06-22",
      "open_interest": 190545,
      "comm_long": 138242,
      "comm_short": 62072,
      "comm_net": 76170,
      "noncomm_long": 34118,
      "noncomm_short": 87980,
      "noncomm_net": -53862,
      "nonrept_net": -22308
    },
    {
      "week": "2021-06-29",
      "open_interest": 195698,
      "comm_long": 149165,
      "comm_short": 57450,
      "comm_net": 91715,
      "noncomm_long": 27380,
      "noncomm_short": 97275,
      "noncomm_net": -69895,
      "nonrept_net": -21820
    },
    {
      "week": "2021-07-06",
      "open_interest": 205341,
      "comm_long": 155707,
      "comm_short": 63576,
      "comm_net": 92131,
      "noncomm_long": 31625,
      "noncomm_short": 100761,
      "noncomm_net": -69136,
      "nonrept_net": -22995
    },
    {
      "week": "2021-07-13",
      "open_interest": 203727,
      "comm_long": 145716,
      "comm_short": 70980,
      "comm_net": 74736,
      "noncomm_long": 40440,
      "noncomm_short": 96690,
      "noncomm_net": -56250,
      "nonrept_net": -18486
    },
    {
      "week": "2021-07-20",
      "open_interest": 192301,
      "comm_long": 138577,
      "comm_short": 67311,
      "comm_net": 71266,
      "noncomm_long": 35474,
      "noncomm_short": 91205,
      "noncomm_net": -55731,
      "nonrept_net": -15535
    },
    {
      "week": "2021-07-27",
      "open_interest": 196102,
      "comm_long": 143819,
      "comm_short": 68805,
      "comm_net": 75014,
      "noncomm_long": 32975,
      "noncomm_short": 92909,
      "noncomm_net": -59934,
      "nonrept_net": -15080
    },
    {
      "week": "2021-08-03",
      "open_interest": 189242,
      "comm_long": 136596,
      "comm_short": 68989,
      "comm_net": 67607,
      "noncomm_long": 30409,
      "noncomm_short": 85599,
      "noncomm_net": -55190,
      "nonrept_net": -12417
    },
    {
      "week": "2021-08-10",
      "open_interest": 206131,
      "comm_long": 151720,
      "comm_short": 68459,
      "comm_net": 83261,
      "noncomm_long": 36684,
      "noncomm_short": 97341,
      "noncomm_net": -60657,
      "nonrept_net": -22604
    },
    {
      "week": "2021-08-17",
      "open_interest": 196495,
      "comm_long": 147403,
      "comm_short": 69312,
      "comm_net": 78091,
      "noncomm_long": 27532,
      "noncomm_short": 90740,
      "noncomm_net": -63208,
      "nonrept_net": -14883
    },
    {
      "week": "2021-08-24",
      "open_interest": 194477,
      "comm_long": 147612,
      "comm_short": 65542,
      "comm_net": 82070,
      "noncomm_long": 26763,
      "noncomm_short": 93434,
      "noncomm_net": -66671,
      "nonrept_net": -15399
    },
    {
      "week": "2021-08-31",
      "open_interest": 193999,
      "comm_long": 144849,
      "comm_short": 65434,
      "comm_net": 79415,
      "noncomm_long": 29030,
      "noncomm_short": 92160,
      "noncomm_net": -63130,
      "nonrept_net": -16285
    },
    {
      "week": "2021-09-07",
      "open_interest": 204435,
      "comm_long": 151585,
      "comm_short": 73003,
      "comm_net": 78582,
      "noncomm_long": 29704,
      "noncomm_short": 92029,
      "noncomm_net": -62325,
      "nonrept_net": -16257
    },
    {
      "week": "2021-09-14",
      "open_interest": 192088,
      "comm_long": 146716,
      "comm_short": 78681,
      "comm_net": 68035,
      "noncomm_long": 21728,
      "noncomm_short": 82023,
      "noncomm_net": -60295,
      "nonrept_net": -7740
    },
    {
      "week": "2021-09-21",
      "open_interest": 191213,
      "comm_long": 146680,
      "comm_short": 80086,
      "comm_net": 66594,
      "noncomm_long": 22844,
      "noncomm_short": 78915,
      "noncomm_net": -56071,
      "nonrept_net": -10523
    },
    {
      "week": "2021-09-28",
      "open_interest": 219638,
      "comm_long": 165246,
      "comm_short": 81967,
      "comm_net": 83279,
      "noncomm_long": 35328,
      "noncomm_short": 100088,
      "noncomm_net": -64760,
      "nonrept_net": -18519
    },
    {
      "week": "2021-10-05",
      "open_interest": 226379,
      "comm_long": 175160,
      "comm_short": 90697,
      "comm_net": 84463,
      "noncomm_long": 31569,
      "noncomm_short": 95263,
      "noncomm_net": -63694,
      "nonrept_net": -20769
    },
    {
      "week": "2021-10-12",
      "open_interest": 243617,
      "comm_long": 185560,
      "comm_short": 90468,
      "comm_net": 95092,
      "noncomm_long": 35810,
      "noncomm_short": 112444,
      "noncomm_net": -76634,
      "nonrept_net": -18458
    },
    {
      "week": "2021-10-19",
      "open_interest": 266750,
      "comm_long": 207735,
      "comm_short": 85095,
      "comm_net": 122640,
      "noncomm_long": 35713,
      "noncomm_short": 138447,
      "noncomm_net": -102734,
      "nonrept_net": -19906
    },
    {
      "week": "2021-10-26",
      "open_interest": 265254,
      "comm_long": 212303,
      "comm_short": 83757,
      "comm_net": 128546,
      "noncomm_long": 31487,
      "noncomm_short": 138523,
      "noncomm_net": -107036,
      "nonrept_net": -21510
    },
    {
      "week": "2021-11-02",
      "open_interest": 251058,
      "comm_long": 207612,
      "comm_short": 81607,
      "comm_net": 126005,
      "noncomm_long": 20337,
      "noncomm_short": 127961,
      "noncomm_net": -107624,
      "nonrept_net": -18381
    },
    {
      "week": "2021-11-09",
      "open_interest": 243087,
      "comm_long": 203044,
      "comm_short": 79845,
      "comm_net": 123199,
      "noncomm_long": 16440,
      "noncomm_short": 121791,
      "noncomm_net": -105351,
      "nonrept_net": -17848
    },
    {
      "week": "2021-11-16",
      "open_interest": 252897,
      "comm_long": 203468,
      "comm_short": 87710,
      "comm_net": 115758,
      "noncomm_long": 24635,
      "noncomm_short": 117761,
      "noncomm_net": -93126,
      "nonrept_net": -22632
    },
    {
      "week": "2021-11-23",
      "open_interest": 251801,
      "comm_long": 205923,
      "comm_short": 89698,
      "comm_net": 116225,
      "noncomm_long": 20285,
      "noncomm_short": 117538,
      "noncomm_net": -97253,
      "nonrept_net": -18972
    },
    {
      "week": "2021-11-30",
      "open_interest": 216692,
      "comm_long": 177285,
      "comm_short": 85252,
      "comm_net": 92033,
      "noncomm_long": 14585,
      "noncomm_short": 93451,
      "noncomm_net": -78866,
      "nonrept_net": -13167
    },
    {
      "week": "2021-12-07",
      "open_interest": 205970,
      "comm_long": 163847,
      "comm_short": 83350,
      "comm_net": 80497,
      "noncomm_long": 13148,
      "noncomm_short": 76229,
      "noncomm_net": -63081,
      "nonrept_net": -17416
    },
    {
      "week": "2021-12-14",
      "open_interest": 176584,
      "comm_long": 136938,
      "comm_short": 65878,
      "comm_net": 71060,
      "noncomm_long": 20231,
      "noncomm_short": 73754,
      "noncomm_net": -53523,
      "nonrept_net": -17537
    },
    {
      "week": "2021-12-21",
      "open_interest": 183743,
      "comm_long": 142161,
      "comm_short": 71002,
      "comm_net": 71159,
      "noncomm_long": 22191,
      "noncomm_short": 74477,
      "noncomm_net": -52286,
      "nonrept_net": -18873
    },
    {
      "week": "2021-12-28",
      "open_interest": 203814,
      "comm_long": 150647,
      "comm_short": 78283,
      "comm_net": 72364,
      "noncomm_long": 32475,
      "noncomm_short": 85577,
      "noncomm_net": -53102,
      "nonrept_net": -19262
    },
    {
      "week": "2022-01-04",
      "open_interest": 234068,
      "comm_long": 170537,
      "comm_short": 85793,
      "comm_net": 84744,
      "noncomm_long": 40816,
      "noncomm_short": 103078,
      "noncomm_net": -62262,
      "nonrept_net": -22482
    },
    {
      "week": "2022-01-11",
      "open_interest": 234005,
      "comm_long": 189708,
      "comm_short": 81316,
      "comm_net": 108392,
      "noncomm_long": 22364,
      "noncomm_short": 109889,
      "noncomm_net": -87525,
      "nonrept_net": -20867
    },
    {
      "week": "2022-01-18",
      "open_interest": 201820,
      "comm_long": 173701,
      "comm_short": 73961,
      "comm_net": 99740,
      "noncomm_long": 8002,
      "noncomm_short": 88881,
      "noncomm_net": -80879,
      "nonrept_net": -18861
    },
    {
      "week": "2022-01-25",
      "open_interest": 197830,
      "comm_long": 160178,
      "comm_short": 77315,
      "comm_net": 82863,
      "noncomm_long": 15866,
      "noncomm_short": 84139,
      "noncomm_net": -68273,
      "nonrept_net": -14590
    },
    {
      "week": "2022-02-01",
      "open_interest": 194435,
      "comm_long": 160358,
      "comm_short": 81005,
      "comm_net": 79353,
      "noncomm_long": 14510,
      "noncomm_short": 75150,
      "noncomm_net": -60640,
      "nonrept_net": -18713
    },
    {
      "week": "2022-02-08",
      "open_interest": 196478,
      "comm_long": 159601,
      "comm_short": 83644,
      "comm_net": 75957,
      "noncomm_long": 15692,
      "noncomm_short": 74840,
      "noncomm_net": -59148,
      "nonrept_net": -16809
    },
    {
      "week": "2022-02-15",
      "open_interest": 199425,
      "comm_long": 166645,
      "comm_short": 80389,
      "comm_net": 86256,
      "noncomm_long": 10425,
      "noncomm_short": 76587,
      "noncomm_net": -66162,
      "nonrept_net": -20094
    },
    {
      "week": "2022-02-22",
      "open_interest": 194169,
      "comm_long": 162044,
      "comm_short": 79564,
      "comm_net": 82480,
      "noncomm_long": 10976,
      "noncomm_short": 74163,
      "noncomm_net": -63187,
      "nonrept_net": -19293
    },
    {
      "week": "2022-03-01",
      "open_interest": 208629,
      "comm_long": 167605,
      "comm_short": 88070,
      "comm_net": 79535,
      "noncomm_long": 14665,
      "noncomm_short": 83397,
      "noncomm_net": -68732,
      "nonrept_net": -10803
    },
    {
      "week": "2022-03-08",
      "open_interest": 208683,
      "comm_long": 170330,
      "comm_short": 93673,
      "comm_net": 76657,
      "noncomm_long": 15548,
      "noncomm_short": 71404,
      "noncomm_net": -55856,
      "nonrept_net": -20801
    },
    {
      "week": "2022-03-15",
      "open_interest": 215484,
      "comm_long": 163089,
      "comm_short": 75492,
      "comm_net": 87597,
      "noncomm_long": 34016,
      "noncomm_short": 96356,
      "noncomm_net": -62340,
      "nonrept_net": -25257
    },
    {
      "week": "2022-03-22",
      "open_interest": 248221,
      "comm_long": 189100,
      "comm_short": 84310,
      "comm_net": 104790,
      "noncomm_long": 36676,
      "noncomm_short": 115158,
      "noncomm_net": -78482,
      "nonrept_net": -26308
    },
    {
      "week": "2022-03-29",
      "open_interest": 239698,
      "comm_long": 201190,
      "comm_short": 76340,
      "comm_net": 124850,
      "noncomm_long": 15274,
      "noncomm_short": 117405,
      "noncomm_net": -102131,
      "nonrept_net": -22719
    },
    {
      "week": "2022-04-05",
      "open_interest": 242217,
      "comm_long": 205209,
      "comm_short": 79985,
      "comm_net": 125224,
      "noncomm_long": 14583,
      "noncomm_short": 118412,
      "noncomm_net": -103829,
      "nonrept_net": -21395
    },
    {
      "week": "2022-04-12",
      "open_interest": 245403,
      "comm_long": 212850,
      "comm_short": 80948,
      "comm_net": 131902,
      "noncomm_long": 9925,
      "noncomm_short": 121752,
      "noncomm_net": -111827,
      "nonrept_net": -20075
    },
    {
      "week": "2022-04-19",
      "open_interest": 251291,
      "comm_long": 216101,
      "comm_short": 86259,
      "comm_net": 129842,
      "noncomm_long": 12723,
      "noncomm_short": 119910,
      "noncomm_net": -107187,
      "nonrept_net": -22655
    },
    {
      "week": "2022-04-26",
      "open_interest": 237995,
      "comm_long": 201828,
      "comm_short": 86907,
      "comm_net": 114921,
      "noncomm_long": 14269,
      "noncomm_short": 109804,
      "noncomm_net": -95535,
      "nonrept_net": -19386
    },
    {
      "week": "2022-05-03",
      "open_interest": 254813,
      "comm_long": 215563,
      "comm_short": 95299,
      "comm_net": 120264,
      "noncomm_long": 18585,
      "noncomm_short": 119379,
      "noncomm_net": -100794,
      "nonrept_net": -19470
    },
    {
      "week": "2022-05-10",
      "open_interest": 247278,
      "comm_long": 213084,
      "comm_short": 88157,
      "comm_net": 124927,
      "noncomm_long": 11196,
      "noncomm_short": 121650,
      "noncomm_net": -110454,
      "nonrept_net": -14473
    },
    {
      "week": "2022-05-17",
      "open_interest": 241308,
      "comm_long": 204417,
      "comm_short": 89355,
      "comm_net": 115062,
      "noncomm_long": 12113,
      "noncomm_short": 114422,
      "noncomm_net": -102309,
      "nonrept_net": -12753
    },
    {
      "week": "2022-05-24",
      "open_interest": 237256,
      "comm_long": 192215,
      "comm_short": 85516,
      "comm_net": 106699,
      "noncomm_long": 16567,
      "noncomm_short": 116011,
      "noncomm_net": -99444,
      "nonrept_net": -7255
    },
    {
      "week": "2022-05-31",
      "open_interest": 239080,
      "comm_long": 196584,
      "comm_short": 91535,
      "comm_net": 105049,
      "noncomm_long": 15201,
      "noncomm_short": 109640,
      "noncomm_net": -94439,
      "nonrept_net": -10610
    },
    {
      "week": "2022-06-07",
      "open_interest": 266054,
      "comm_long": 210889,
      "comm_short": 101780,
      "comm_net": 109109,
      "noncomm_long": 18466,
      "noncomm_short": 110112,
      "noncomm_net": -91646,
      "nonrept_net": -17463
    },
    {
      "week": "2022-06-14",
      "open_interest": 232513,
      "comm_long": 175789,
      "comm_short": 89346,
      "comm_net": 86443,
      "noncomm_long": 32441,
      "noncomm_short": 102196,
      "noncomm_net": -69755,
      "nonrept_net": -16688
    },
    {
      "week": "2022-06-21",
      "open_interest": 218076,
      "comm_long": 156248,
      "comm_short": 81899,
      "comm_net": 74349,
      "noncomm_long": 35864,
      "noncomm_short": 94318,
      "noncomm_net": -58454,
      "nonrept_net": -15895
    },
    {
      "week": "2022-06-28",
      "open_interest": 213767,
      "comm_long": 152071,
      "comm_short": 84176,
      "comm_net": 67895,
      "noncomm_long": 36462,
      "noncomm_short": 89032,
      "noncomm_net": -52570,
      "nonrept_net": -15325
    },
    {
      "week": "2022-07-05",
      "open_interest": 217672,
      "comm_long": 149702,
      "comm_short": 85639,
      "comm_net": 64063,
      "noncomm_long": 38660,
      "noncomm_short": 93105,
      "noncomm_net": -54445,
      "nonrept_net": -9618
    },
    {
      "week": "2022-07-12",
      "open_interest": 223539,
      "comm_long": 160589,
      "comm_short": 85522,
      "comm_net": 75067,
      "noncomm_long": 35533,
      "noncomm_short": 95531,
      "noncomm_net": -59998,
      "nonrept_net": -15069
    },
    {
      "week": "2022-07-19",
      "open_interest": 229449,
      "comm_long": 158427,
      "comm_short": 85345,
      "comm_net": 73082,
      "noncomm_long": 42880,
      "noncomm_short": 102105,
      "noncomm_net": -59225,
      "nonrept_net": -13857
    },
    {
      "week": "2022-07-26",
      "open_interest": 229219,
      "comm_long": 157963,
      "comm_short": 84190,
      "comm_net": 73773,
      "noncomm_long": 43812,
      "noncomm_short": 105293,
      "noncomm_net": -61481,
      "nonrept_net": -12292
    },
    {
      "week": "2022-08-02",
      "open_interest": 236737,
      "comm_long": 157333,
      "comm_short": 107079,
      "comm_net": 50254,
      "noncomm_long": 50433,
      "noncomm_short": 93186,
      "noncomm_net": -42753,
      "nonrept_net": -7501
    },
    {
      "week": "2022-08-09",
      "open_interest": 225834,
      "comm_long": 148628,
      "comm_short": 111634,
      "comm_net": 36994,
      "noncomm_long": 52333,
      "noncomm_short": 77365,
      "noncomm_net": -25032,
      "nonrept_net": -11962
    },
    {
      "week": "2022-08-16",
      "open_interest": 228697,
      "comm_long": 152209,
      "comm_short": 110230,
      "comm_net": 41979,
      "noncomm_long": 51308,
      "noncomm_short": 80199,
      "noncomm_net": -28891,
      "nonrept_net": -13088
    },
    {
      "week": "2022-08-23",
      "open_interest": 242132,
      "comm_long": 156987,
      "comm_short": 104523,
      "comm_net": 52464,
      "noncomm_long": 56734,
      "noncomm_short": 95541,
      "noncomm_net": -38807,
      "nonrept_net": -13657
    },
    {
      "week": "2022-08-30",
      "open_interest": 247030,
      "comm_long": 163991,
      "comm_short": 102704,
      "comm_net": 61287,
      "noncomm_long": 54513,
      "noncomm_short": 96044,
      "noncomm_net": -41531,
      "nonrept_net": -19756
    },
    {
      "week": "2022-09-06",
      "open_interest": 281266,
      "comm_long": 191138,
      "comm_short": 113469,
      "comm_net": 77669,
      "noncomm_long": 56002,
      "noncomm_short": 114191,
      "noncomm_net": -58189,
      "nonrept_net": -19480
    },
    {
      "week": "2022-09-13",
      "open_interest": 281716,
      "comm_long": 212375,
      "comm_short": 114076,
      "comm_net": 98299,
      "noncomm_long": 39323,
      "noncomm_short": 120015,
      "noncomm_net": -80692,
      "nonrept_net": -17607
    },
    {
      "week": "2022-09-20",
      "open_interest": 250892,
      "comm_long": 190267,
      "comm_short": 92754,
      "comm_net": 97513,
      "noncomm_long": 34767,
      "noncomm_short": 116047,
      "noncomm_net": -81280,
      "nonrept_net": -16233
    },
    {
      "week": "2022-09-27",
      "open_interest": 244655,
      "comm_long": 195930,
      "comm_short": 95297,
      "comm_net": 100633,
      "noncomm_long": 22706,
      "noncomm_short": 105262,
      "noncomm_net": -82556,
      "nonrept_net": -18077
    },
    {
      "week": "2022-10-04",
      "open_interest": 243289,
      "comm_long": 185691,
      "comm_short": 92367,
      "comm_net": 93324,
      "noncomm_long": 26962,
      "noncomm_short": 108585,
      "noncomm_net": -81623,
      "nonrept_net": -11701
    },
    {
      "week": "2022-10-11",
      "open_interest": 245007,
      "comm_long": 187119,
      "comm_short": 92670,
      "comm_net": 94449,
      "noncomm_long": 30149,
      "noncomm_short": 107542,
      "noncomm_net": -77393,
      "nonrept_net": -17056
    },
    {
      "week": "2022-10-18",
      "open_interest": 264265,
      "comm_long": 203508,
      "comm_short": 92667,
      "comm_net": 110841,
      "noncomm_long": 30583,
      "noncomm_short": 124919,
      "noncomm_net": -94336,
      "nonrept_net": -16505
    },
    {
      "week": "2022-10-25",
      "open_interest": 272597,
      "comm_long": 205120,
      "comm_short": 87038,
      "comm_net": 118082,
      "noncomm_long": 37579,
      "noncomm_short": 140197,
      "noncomm_net": -102618,
      "nonrept_net": -15464
    },
    {
      "week": "2022-11-01",
      "open_interest": 258906,
      "comm_long": 191221,
      "comm_short": 95447,
      "comm_net": 95774,
      "noncomm_long": 40460,
      "noncomm_short": 118080,
      "noncomm_net": -77620,
      "nonrept_net": -18154
    },
    {
      "week": "2022-11-08",
      "open_interest": 251378,
      "comm_long": 183539,
      "comm_short": 94559,
      "comm_net": 88980,
      "noncomm_long": 37201,
      "noncomm_short": 112459,
      "noncomm_net": -75258,
      "nonrept_net": -13722
    },
    {
      "week": "2022-11-15",
      "open_interest": 233346,
      "comm_long": 172905,
      "comm_short": 95692,
      "comm_net": 77213,
      "noncomm_long": 33797,
      "noncomm_short": 99639,
      "noncomm_net": -65842,
      "nonrept_net": -11371
    },
    {
      "week": "2022-11-22",
      "open_interest": 227435,
      "comm_long": 170350,
      "comm_short": 92244,
      "comm_net": 78106,
      "noncomm_long": 30800,
      "noncomm_short": 95650,
      "noncomm_net": -64850,
      "nonrept_net": -13256
    },
    {
      "week": "2022-11-29",
      "open_interest": 228328,
      "comm_long": 173959,
      "comm_short": 91290,
      "comm_net": 82669,
      "noncomm_long": 28125,
      "noncomm_short": 95519,
      "noncomm_net": -67394,
      "nonrept_net": -15275
    },
    {
      "week": "2022-12-06",
      "open_interest": 223424,
      "comm_long": 169918,
      "comm_short": 94716,
      "comm_net": 75202,
      "noncomm_long": 23589,
      "noncomm_short": 89585,
      "noncomm_net": -65996,
      "nonrept_net": -9206
    },
    {
      "week": "2022-12-13",
      "open_interest": 226964,
      "comm_long": 157021,
      "comm_short": 97992,
      "comm_net": 59029,
      "noncomm_long": 22290,
      "noncomm_short": 75478,
      "noncomm_net": -53188,
      "nonrept_net": -5841
    },
    {
      "week": "2022-12-20",
      "open_interest": 182034,
      "comm_long": 121482,
      "comm_short": 75759,
      "comm_net": 45723,
      "noncomm_long": 33686,
      "noncomm_short": 74567,
      "noncomm_net": -40881,
      "nonrept_net": -4842
    },
    {
      "week": "2022-12-27",
      "open_interest": 173136,
      "comm_long": 118599,
      "comm_short": 72598,
      "comm_net": 46001,
      "noncomm_long": 29685,
      "noncomm_short": 67415,
      "noncomm_net": -37730,
      "nonrept_net": -8271
    },
    {
      "week": "2023-01-03",
      "open_interest": 172590,
      "comm_long": 117959,
      "comm_short": 71186,
      "comm_net": 46773,
      "noncomm_long": 25377,
      "noncomm_short": 72241,
      "noncomm_net": -46864,
      "nonrept_net": 91
    },
    {
      "week": "2023-01-10",
      "open_interest": 175745,
      "comm_long": 119166,
      "comm_short": 84678,
      "comm_net": 34488,
      "noncomm_long": 26395,
      "noncomm_short": 61772,
      "noncomm_net": -35377,
      "nonrept_net": 889
    },
    {
      "week": "2023-01-17",
      "open_interest": 176862,
      "comm_long": 114907,
      "comm_short": 96823,
      "comm_net": 18084,
      "noncomm_long": 29458,
      "noncomm_short": 52419,
      "noncomm_net": -22961,
      "nonrept_net": 4877
    },
    {
      "week": "2023-01-24",
      "open_interest": 173321,
      "comm_long": 113437,
      "comm_short": 96292,
      "comm_net": 17145,
      "noncomm_long": 27620,
      "noncomm_short": 49255,
      "noncomm_net": -21635,
      "nonrept_net": 4490
    },
    {
      "week": "2023-01-31",
      "open_interest": 168540,
      "comm_long": 114423,
      "comm_short": 96244,
      "comm_net": 18179,
      "noncomm_long": 22550,
      "noncomm_short": 42610,
      "noncomm_net": -20060,
      "nonrept_net": 1881
    },
    {
      "week": "2023-02-07",
      "open_interest": 164069,
      "comm_long": 118080,
      "comm_short": 84734,
      "comm_net": 33346,
      "noncomm_long": 16556,
      "noncomm_short": 45645,
      "noncomm_net": -29089,
      "nonrept_net": -4257
    },
    {
      "week": "2023-02-14",
      "open_interest": 174955,
      "comm_long": 124522,
      "comm_short": 88753,
      "comm_net": 35769,
      "noncomm_long": 23079,
      "noncomm_short": 50922,
      "noncomm_net": -27843,
      "nonrept_net": -7926
    },
    {
      "week": "2023-02-21",
      "open_interest": 186100,
      "comm_long": 126777,
      "comm_short": 79888,
      "comm_net": 46889,
      "noncomm_long": 32486,
      "noncomm_short": 66515,
      "noncomm_net": -34029,
      "nonrept_net": -12860
    },
    {
      "week": "2023-02-28",
      "open_interest": 200047,
      "comm_long": 142893,
      "comm_short": 72372,
      "comm_net": 70521,
      "noncomm_long": 27703,
      "noncomm_short": 86381,
      "noncomm_net": -58678,
      "nonrept_net": -11843
    },
    {
      "week": "2023-03-07",
      "open_interest": 211297,
      "comm_long": 163246,
      "comm_short": 73643,
      "comm_net": 89603,
      "noncomm_long": 17141,
      "noncomm_short": 92444,
      "noncomm_net": -75303,
      "nonrept_net": -14300
    },
    {
      "week": "2023-03-14",
      "open_interest": 179782,
      "comm_long": 142857,
      "comm_short": 56863,
      "comm_net": 85994,
      "noncomm_long": 11048,
      "noncomm_short": 85842,
      "noncomm_net": -74794,
      "nonrept_net": -11200
    },
    {
      "week": "2023-03-21",
      "open_interest": 169188,
      "comm_long": 134389,
      "comm_short": 61905,
      "comm_net": 72484,
      "noncomm_long": 7255,
      "noncomm_short": 73600,
      "noncomm_net": -66345,
      "nonrept_net": -6139
    },
    {
      "week": "2023-03-28",
      "open_interest": 169473,
      "comm_long": 132070,
      "comm_short": 74508,
      "comm_net": 57562,
      "noncomm_long": 9717,
      "noncomm_short": 63692,
      "noncomm_net": -53975,
      "nonrept_net": -3587
    },
    {
      "week": "2023-04-04",
      "open_interest": 178828,
      "comm_long": 133327,
      "comm_short": 81061,
      "comm_net": 52266,
      "noncomm_long": 11523,
      "noncomm_short": 68559,
      "noncomm_net": -57036,
      "nonrept_net": 4770
    },
    {
      "week": "2023-04-11",
      "open_interest": 176822,
      "comm_long": 132604,
      "comm_short": 76255,
      "comm_net": 56349,
      "noncomm_long": 11933,
      "noncomm_short": 69140,
      "noncomm_net": -57207,
      "nonrept_net": 858
    },
    {
      "week": "2023-04-18",
      "open_interest": 177507,
      "comm_long": 132747,
      "comm_short": 71102,
      "comm_net": 61645,
      "noncomm_long": 15661,
      "noncomm_short": 72530,
      "noncomm_net": -56869,
      "nonrept_net": -4776
    },
    {
      "week": "2023-04-25",
      "open_interest": 184041,
      "comm_long": 135330,
      "comm_short": 62705,
      "comm_net": 72625,
      "noncomm_long": 13680,
      "noncomm_short": 82424,
      "noncomm_net": -68744,
      "nonrept_net": -3881
    },
    {
      "week": "2023-05-02",
      "open_interest": 202996,
      "comm_long": 141332,
      "comm_short": 63811,
      "comm_net": 77521,
      "noncomm_long": 28088,
      "noncomm_short": 96412,
      "noncomm_net": -68324,
      "nonrept_net": -9197
    },
    {
      "week": "2023-05-09",
      "open_interest": 192574,
      "comm_long": 137992,
      "comm_short": 68830,
      "comm_net": 69162,
      "noncomm_long": 22229,
      "noncomm_short": 83244,
      "noncomm_net": -61015,
      "nonrept_net": -8147
    },
    {
      "week": "2023-05-16",
      "open_interest": 200515,
      "comm_long": 142392,
      "comm_short": 66255,
      "comm_net": 76137,
      "noncomm_long": 29494,
      "noncomm_short": 94285,
      "noncomm_net": -64791,
      "nonrept_net": -11346
    },
    {
      "week": "2023-05-23",
      "open_interest": 226400,
      "comm_long": 157498,
      "comm_short": 65120,
      "comm_net": 92378,
      "noncomm_long": 36760,
      "noncomm_short": 117420,
      "noncomm_net": -80660,
      "nonrept_net": -11718
    },
    {
      "week": "2023-05-30",
      "open_interest": 243237,
      "comm_long": 166931,
      "comm_short": 60419,
      "comm_net": 106512,
      "noncomm_long": 40736,
      "noncomm_short": 136929,
      "noncomm_net": -96193,
      "nonrept_net": -10319
    },
    {
      "week": "2023-06-06",
      "open_interest": 245332,
      "comm_long": 174461,
      "comm_short": 60725,
      "comm_net": 113736,
      "noncomm_long": 34151,
      "noncomm_short": 138968,
      "noncomm_net": -104817,
      "nonrept_net": -8919
    },
    {
      "week": "2023-06-13",
      "open_interest": 252566,
      "comm_long": 175067,
      "comm_short": 56886,
      "comm_net": 118181,
      "noncomm_long": 37088,
      "noncomm_short": 141064,
      "noncomm_net": -103976,
      "nonrept_net": -14205
    },
    {
      "week": "2023-06-20",
      "open_interest": 238556,
      "comm_long": 175201,
      "comm_short": 56929,
      "comm_net": 118272,
      "noncomm_long": 32244,
      "noncomm_short": 139900,
      "noncomm_net": -107656,
      "nonrept_net": -10616
    },
    {
      "week": "2023-06-27",
      "open_interest": 251524,
      "comm_long": 181511,
      "comm_short": 59145,
      "comm_net": 122366,
      "noncomm_long": 38018,
      "noncomm_short": 150888,
      "noncomm_net": -112870,
      "nonrept_net": -9496
    },
    {
      "week": "2023-07-03",
      "open_interest": 265066,
      "comm_long": 190157,
      "comm_short": 64147,
      "comm_net": 126010,
      "noncomm_long": 41713,
      "noncomm_short": 159633,
      "noncomm_net": -117920,
      "nonrept_net": -8090
    },
    {
      "week": "2023-07-11",
      "open_interest": 252349,
      "comm_long": 190189,
      "comm_short": 61112,
      "comm_net": 129077,
      "noncomm_long": 29838,
      "noncomm_short": 147020,
      "noncomm_net": -117182,
      "nonrept_net": -11895
    },
    {
      "week": "2023-07-18",
      "open_interest": 230932,
      "comm_long": 170491,
      "comm_short": 72296,
      "comm_net": 98195,
      "noncomm_long": 29776,
      "noncomm_short": 120015,
      "noncomm_net": -90239,
      "nonrept_net": -7956
    },
    {
      "week": "2023-07-25",
      "open_interest": 223760,
      "comm_long": 161166,
      "comm_short": 74611,
      "comm_net": 86555,
      "noncomm_long": 30358,
      "noncomm_short": 108110,
      "noncomm_net": -77752,
      "nonrept_net": -8803
    },
    {
      "week": "2023-08-01",
      "open_interest": 229015,
      "comm_long": 164659,
      "comm_short": 81371,
      "comm_net": 83288,
      "noncomm_long": 26849,
      "noncomm_short": 106065,
      "noncomm_net": -79216,
      "nonrept_net": -4072
    },
    {
      "week": "2023-08-08",
      "open_interest": 229849,
      "comm_long": 169528,
      "comm_short": 80407,
      "comm_net": 89121,
      "noncomm_long": 23135,
      "noncomm_short": 106315,
      "noncomm_net": -83180,
      "nonrept_net": -5941
    },
    {
      "week": "2023-08-15",
      "open_interest": 247954,
      "comm_long": 175636,
      "comm_short": 85139,
      "comm_net": 90497,
      "noncomm_long": 34789,
      "noncomm_short": 115750,
      "noncomm_net": -80961,
      "nonrept_net": -9536
    },
    {
      "week": "2023-08-22",
      "open_interest": 246923,
      "comm_long": 180967,
      "comm_short": 76343,
      "comm_net": 104624,
      "noncomm_long": 28680,
      "noncomm_short": 124003,
      "noncomm_net": -95323,
      "nonrept_net": -9301
    },
    {
      "week": "2023-08-29",
      "open_interest": 245452,
      "comm_long": 181043,
      "comm_short": 77975,
      "comm_net": 103068,
      "noncomm_long": 24790,
      "noncomm_short": 123263,
      "noncomm_net": -98473,
      "nonrept_net": -4595
    },
    {
      "week": "2023-09-05",
      "open_interest": 268344,
      "comm_long": 190804,
      "comm_short": 84937,
      "comm_net": 105867,
      "noncomm_long": 37014,
      "noncomm_short": 134150,
      "noncomm_net": -97136,
      "nonrept_net": -8731
    },
    {
      "week": "2023-09-12",
      "open_interest": 270854,
      "comm_long": 183589,
      "comm_short": 76945,
      "comm_net": 106644,
      "noncomm_long": 38247,
      "noncomm_short": 136960,
      "noncomm_net": -98713,
      "nonrept_net": -7931
    },
    {
      "week": "2023-09-19",
      "open_interest": 265860,
      "comm_long": 183927,
      "comm_short": 72482,
      "comm_net": 111445,
      "noncomm_long": 45737,
      "noncomm_short": 147356,
      "noncomm_net": -101619,
      "nonrept_net": -9826
    },
    {
      "week": "2023-09-26",
      "open_interest": 285974,
      "comm_long": 200015,
      "comm_short": 79788,
      "comm_net": 120227,
      "noncomm_long": 46169,
      "noncomm_short": 155681,
      "noncomm_net": -109512,
      "nonrept_net": -10715
    },
    {
      "week": "2023-10-03",
      "open_interest": 282682,
      "comm_long": 194193,
      "comm_short": 76324,
      "comm_net": 117869,
      "noncomm_long": 47544,
      "noncomm_short": 161532,
      "noncomm_net": -113988,
      "nonrept_net": -3881
    },
    {
      "week": "2023-10-10",
      "open_interest": 259937,
      "comm_long": 182514,
      "comm_short": 76362,
      "comm_net": 106152,
      "noncomm_long": 36780,
      "noncomm_short": 136256,
      "noncomm_net": -99476,
      "nonrept_net": -6676
    },
    {
      "week": "2023-10-17",
      "open_interest": 267521,
      "comm_long": 193634,
      "comm_short": 81275,
      "comm_net": 112359,
      "noncomm_long": 33139,
      "noncomm_short": 135797,
      "noncomm_net": -102658,
      "nonrept_net": -9701
    },
    {
      "week": "2023-10-24",
      "open_interest": 260909,
      "comm_long": 186381,
      "comm_short": 81572,
      "comm_net": 104809,
      "noncomm_long": 30964,
      "noncomm_short": 130593,
      "noncomm_net": -99629,
      "nonrept_net": -5180
    },
    {
      "week": "2023-10-31",
      "open_interest": 277272,
      "comm_long": 193460,
      "comm_short": 85894,
      "comm_net": 107566,
      "noncomm_long": 37641,
      "noncomm_short": 141489,
      "noncomm_net": -103848,
      "nonrept_net": -3718
    },
    {
      "week": "2023-11-07",
      "open_interest": 259698,
      "comm_long": 189951,
      "comm_short": 77994,
      "comm_net": 111957,
      "noncomm_long": 27238,
      "noncomm_short": 131278,
      "noncomm_net": -104040,
      "nonrept_net": -7917
    },
    {
      "week": "2023-11-14",
      "open_interest": 273763,
      "comm_long": 199890,
      "comm_short": 66618,
      "comm_net": 133272,
      "noncomm_long": 27772,
      "noncomm_short": 158021,
      "noncomm_net": -130249,
      "nonrept_net": -3023
    },
    {
      "week": "2023-11-21",
      "open_interest": 264903,
      "comm_long": 178832,
      "comm_short": 73404,
      "comm_net": 105428,
      "noncomm_long": 39236,
      "noncomm_short": 144690,
      "noncomm_net": -105454,
      "nonrept_net": 26
    },
    {
      "week": "2023-11-28",
      "open_interest": 260781,
      "comm_long": 180134,
      "comm_short": 76442,
      "comm_net": 103692,
      "noncomm_long": 30461,
      "noncomm_short": 139698,
      "noncomm_net": -109237,
      "nonrept_net": 5545
    },
    {
      "week": "2023-12-05",
      "open_interest": 267482,
      "comm_long": 184156,
      "comm_short": 77938,
      "comm_net": 106218,
      "noncomm_long": 28266,
      "noncomm_short": 133222,
      "noncomm_net": -104956,
      "nonrept_net": -1262
    },
    {
      "week": "2023-12-12",
      "open_interest": 257581,
      "comm_long": 172756,
      "comm_short": 93229,
      "comm_net": 79527,
      "noncomm_long": 28226,
      "noncomm_short": 109357,
      "noncomm_net": -81131,
      "nonrept_net": 1604
    },
    {
      "week": "2023-12-19",
      "open_interest": 185940,
      "comm_long": 112422,
      "comm_short": 49729,
      "comm_net": 62693,
      "noncomm_long": 31734,
      "noncomm_short": 96636,
      "noncomm_net": -64902,
      "nonrept_net": 2209
    },
    {
      "week": "2023-12-26",
      "open_interest": 188540,
      "comm_long": 110013,
      "comm_short": 57354,
      "comm_net": 52659,
      "noncomm_long": 37321,
      "noncomm_short": 92889,
      "noncomm_net": -55568,
      "nonrept_net": 2909
    },
    {
      "week": "2024-01-02",
      "open_interest": 184042,
      "comm_long": 108605,
      "comm_short": 53116,
      "comm_net": 55489,
      "noncomm_long": 33585,
      "noncomm_short": 90780,
      "noncomm_net": -57195,
      "nonrept_net": 1706
    },
    {
      "week": "2024-01-09",
      "open_interest": 200299,
      "comm_long": 113876,
      "comm_short": 59685,
      "comm_net": 54191,
      "noncomm_long": 41364,
      "noncomm_short": 97313,
      "noncomm_net": -55949,
      "nonrept_net": 1758
    },
    {
      "week": "2024-01-16",
      "open_interest": 213309,
      "comm_long": 125048,
      "comm_short": 63324,
      "comm_net": 61724,
      "noncomm_long": 44180,
      "noncomm_short": 100740,
      "noncomm_net": -56560,
      "nonrept_net": -5164
    },
    {
      "week": "2024-01-23",
      "open_interest": 243032,
      "comm_long": 144222,
      "comm_short": 67230,
      "comm_net": 76992,
      "noncomm_long": 52585,
      "noncomm_short": 123230,
      "noncomm_net": -70645,
      "nonrept_net": -6347
    },
    {
      "week": "2024-01-30",
      "open_interest": 242029,
      "comm_long": 148972,
      "comm_short": 68838,
      "comm_net": 80134,
      "noncomm_long": 44918,
      "noncomm_short": 125373,
      "noncomm_net": -80455,
      "nonrept_net": 321
    },
    {
      "week": "2024-02-06",
      "open_interest": 259542,
      "comm_long": 155571,
      "comm_short": 72588,
      "comm_net": 82983,
      "noncomm_long": 55646,
      "noncomm_short": 139876,
      "noncomm_net": -84230,
      "nonrept_net": 1247
    },
    {
      "week": "2024-02-13",
      "open_interest": 304592,
      "comm_long": 194067,
      "comm_short": 78895,
      "comm_net": 115172,
      "noncomm_long": 58554,
      "noncomm_short": 170090,
      "noncomm_net": -111536,
      "nonrept_net": -3636
    },
    {
      "week": "2024-02-20",
      "open_interest": 305438,
      "comm_long": 199061,
      "comm_short": 73207,
      "comm_net": 125854,
      "noncomm_long": 53862,
      "noncomm_short": 174640,
      "noncomm_net": -120778,
      "nonrept_net": -5076
    },
    {
      "week": "2024-02-27",
      "open_interest": 309633,
      "comm_long": 204425,
      "comm_short": 72443,
      "comm_net": 131982,
      "noncomm_long": 51261,
      "noncomm_short": 183966,
      "noncomm_net": -132705,
      "nonrept_net": 723
    },
    {
      "week": "2024-03-05",
      "open_interest": 314586,
      "comm_long": 200129,
      "comm_short": 86604,
      "comm_net": 113525,
      "noncomm_long": 54671,
      "noncomm_short": 173514,
      "noncomm_net": -118843,
      "nonrept_net": 5318
    },
    {
      "week": "2024-03-12",
      "open_interest": 325675,
      "comm_long": 207478,
      "comm_short": 109601,
      "comm_net": 97877,
      "noncomm_long": 54923,
      "noncomm_short": 157245,
      "noncomm_net": -102322,
      "nonrept_net": 4445
    },
    {
      "week": "2024-03-19",
      "open_interest": 302500,
      "comm_long": 182299,
      "comm_short": 67180,
      "comm_net": 115119,
      "noncomm_long": 66274,
      "noncomm_short": 182286,
      "noncomm_net": -116012,
      "nonrept_net": 893
    },
    {
      "week": "2024-03-26",
      "open_interest": 305701,
      "comm_long": 194045,
      "comm_short": 64457,
      "comm_net": 129588,
      "noncomm_long": 59969,
      "noncomm_short": 189075,
      "noncomm_net": -129106,
      "nonrept_net": -482
    },
    {
      "week": "2024-04-02",
      "open_interest": 316809,
      "comm_long": 205195,
      "comm_short": 65701,
      "comm_net": 139494,
      "noncomm_long": 55190,
      "noncomm_short": 198420,
      "noncomm_net": -143230,
      "nonrept_net": 3736
    },
    {
      "week": "2024-04-09",
      "open_interest": 324479,
      "comm_long": 219256,
      "comm_short": 62314,
      "comm_net": 156942,
      "noncomm_long": 47275,
      "noncomm_short": 209426,
      "noncomm_net": -162151,
      "nonrept_net": 5209
    },
    {
      "week": "2024-04-16",
      "open_interest": 331110,
      "comm_long": 230642,
      "comm_short": 62900,
      "comm_net": 167742,
      "noncomm_long": 49463,
      "noncomm_short": 215082,
      "noncomm_net": -165619,
      "nonrept_net": -2123
    },
    {
      "week": "2024-04-23",
      "open_interest": 336167,
      "comm_long": 239847,
      "comm_short": 60703,
      "comm_net": 179144,
      "noncomm_long": 42426,
      "noncomm_short": 222345,
      "noncomm_net": -179919,
      "nonrept_net": 775
    },
    {
      "week": "2024-04-30",
      "open_interest": 334848,
      "comm_long": 244920,
      "comm_short": 68798,
      "comm_net": 176122,
      "noncomm_long": 40435,
      "noncomm_short": 208823,
      "noncomm_net": -168388,
      "nonrept_net": -7734
    },
    {
      "week": "2024-05-07",
      "open_interest": 299859,
      "comm_long": 219305,
      "comm_short": 77532,
      "comm_net": 141773,
      "noncomm_long": 34990,
      "noncomm_short": 169912,
      "noncomm_net": -134922,
      "nonrept_net": -6851
    },
    {
      "week": "2024-05-14",
      "open_interest": 297606,
      "comm_long": 216442,
      "comm_short": 83148,
      "comm_net": 133294,
      "noncomm_long": 35303,
      "noncomm_short": 161485,
      "noncomm_net": -126182,
      "nonrept_net": -7112
    },
    {
      "week": "2024-05-21",
      "open_interest": 301315,
      "comm_long": 224424,
      "comm_short": 77907,
      "comm_net": 146517,
      "noncomm_long": 29614,
      "noncomm_short": 173981,
      "noncomm_net": -144367,
      "nonrept_net": -2150
    },
    {
      "week": "2024-05-28",
      "open_interest": 325231,
      "comm_long": 246911,
      "comm_short": 80789,
      "comm_net": 166122,
      "noncomm_long": 28565,
      "noncomm_short": 184604,
      "noncomm_net": -156039,
      "nonrept_net": -10083
    },
    {
      "week": "2024-06-04",
      "open_interest": 303009,
      "comm_long": 204830,
      "comm_short": 74935,
      "comm_net": 129895,
      "noncomm_long": 40427,
      "noncomm_short": 172528,
      "noncomm_net": -132101,
      "nonrept_net": 2206
    },
    {
      "week": "2024-06-11",
      "open_interest": 319274,
      "comm_long": 228809,
      "comm_short": 83182,
      "comm_net": 145627,
      "noncomm_long": 30763,
      "noncomm_short": 169342,
      "noncomm_net": -138579,
      "nonrept_net": -7048
    },
    {
      "week": "2024-06-18",
      "open_interest": 297117,
      "comm_long": 227907,
      "comm_short": 68141,
      "comm_net": 159766,
      "noncomm_long": 29429,
      "noncomm_short": 177182,
      "noncomm_net": -147753,
      "nonrept_net": -12013
    },
    {
      "week": "2024-06-25",
      "open_interest": 340237,
      "comm_long": 259292,
      "comm_short": 77434,
      "comm_net": 181858,
      "noncomm_long": 34576,
      "noncomm_short": 208476,
      "noncomm_net": -173900,
      "nonrept_net": -7958
    },
    {
      "week": "2024-07-02",
      "open_interest": 349817,
      "comm_long": 264603,
      "comm_short": 70058,
      "comm_net": 194545,
      "noncomm_long": 36714,
      "noncomm_short": 220937,
      "noncomm_net": -184223,
      "nonrept_net": -10322
    },
    {
      "week": "2024-07-09",
      "open_interest": 348954,
      "comm_long": 257455,
      "comm_short": 67588,
      "comm_net": 189867,
      "noncomm_long": 41521,
      "noncomm_short": 223554,
      "noncomm_net": -182033,
      "nonrept_net": -7834
    },
    {
      "week": "2024-07-16",
      "open_interest": 307205,
      "comm_long": 216042,
      "comm_short": 56953,
      "comm_net": 159089,
      "noncomm_long": 47356,
      "noncomm_short": 198428,
      "noncomm_net": -151072,
      "nonrept_net": -8017
    },
    {
      "week": "2024-07-23",
      "open_interest": 307183,
      "comm_long": 194534,
      "comm_short": 85766,
      "comm_net": 108768,
      "noncomm_long": 64390,
      "noncomm_short": 171498,
      "noncomm_net": -107108,
      "nonrept_net": -1660
    },
    {
      "week": "2024-07-30",
      "open_interest": 303151,
      "comm_long": 195104,
      "comm_short": 117524,
      "comm_net": 77580,
      "noncomm_long": 65016,
      "noncomm_short": 138476,
      "noncomm_net": -73460,
      "nonrept_net": -4120
    },
    {
      "week": "2024-08-06",
      "open_interest": 298937,
      "comm_long": 191829,
      "comm_short": 179633,
      "comm_net": 12196,
      "noncomm_long": 66169,
      "noncomm_short": 77523,
      "noncomm_net": -11354,
      "nonrept_net": -842
    },
    {
      "week": "2024-08-13",
      "open_interest": 315338,
      "comm_long": 190064,
      "comm_short": 213591,
      "comm_net": -23527,
      "noncomm_long": 87101,
      "noncomm_short": 63997,
      "noncomm_net": 23104,
      "nonrept_net": 423
    },
    {
      "week": "2024-08-20",
      "open_interest": 316197,
      "comm_long": 187055,
      "comm_short": 215456,
      "comm_net": -28401,
      "noncomm_long": 88761,
      "noncomm_short": 65176,
      "noncomm_net": 23585,
      "nonrept_net": 4816
    },
    {
      "week": "2024-08-27",
      "open_interest": 318259,
      "comm_long": 190141,
      "comm_short": 221591,
      "comm_net": -31450,
      "noncomm_long": 84305,
      "noncomm_short": 58437,
      "noncomm_net": 25868,
      "nonrept_net": 5582
    },
    {
      "week": "2024-09-03",
      "open_interest": 326795,
      "comm_long": 189291,
      "comm_short": 236056,
      "comm_net": -46765,
      "noncomm_long": 91791,
      "noncomm_short": 50675,
      "noncomm_net": 41116,
      "nonrept_net": 5649
    },
    {
      "week": "2024-09-10",
      "open_interest": 376514,
      "comm_long": 223698,
      "comm_short": 290417,
      "comm_net": -66719,
      "noncomm_long": 98894,
      "noncomm_short": 43124,
      "noncomm_net": 55770,
      "nonrept_net": 10949
    },
    {
      "week": "2024-09-17",
      "open_interest": 199463,
      "comm_long": 56915,
      "comm_short": 128754,
      "comm_net": -71839,
      "noncomm_long": 97332,
      "noncomm_short": 40492,
      "noncomm_net": 56840,
      "nonrept_net": 14999
    },
    {
      "week": "2024-09-24",
      "open_interest": 207702,
      "comm_long": 58606,
      "comm_short": 136114,
      "comm_net": -77508,
      "noncomm_long": 104690,
      "noncomm_short": 38679,
      "noncomm_net": 66011,
      "nonrept_net": 11497
    },
    {
      "week": "2024-10-01",
      "open_interest": 196200,
      "comm_long": 58635,
      "comm_short": 125382,
      "comm_net": -66747,
      "noncomm_long": 95513,
      "noncomm_short": 38741,
      "noncomm_net": 56772,
      "nonrept_net": 9975
    },
    {
      "week": "2024-10-08",
      "open_interest": 196685,
      "comm_long": 73626,
      "comm_short": 111285,
      "comm_net": -37659,
      "noncomm_long": 83679,
      "noncomm_short": 47151,
      "noncomm_net": 36528,
      "nonrept_net": 1131
    },
    {
      "week": "2024-10-15",
      "open_interest": 197871,
      "comm_long": 68697,
      "comm_short": 105336,
      "comm_net": -36639,
      "noncomm_long": 86685,
      "noncomm_short": 52575,
      "noncomm_net": 34110,
      "nonrept_net": 2529
    },
    {
      "week": "2024-10-22",
      "open_interest": 207338,
      "comm_long": 86382,
      "comm_short": 97010,
      "comm_net": -10628,
      "noncomm_long": 79364,
      "noncomm_short": 66593,
      "noncomm_net": 12771,
      "nonrept_net": -2143
    },
    {
      "week": "2024-10-29",
      "open_interest": 225894,
      "comm_long": 121136,
      "comm_short": 93054,
      "comm_net": 28082,
      "noncomm_long": 64925,
      "noncomm_short": 89742,
      "noncomm_net": -24817,
      "nonrept_net": -3265
    },
    {
      "week": "2024-11-05",
      "open_interest": 235762,
      "comm_long": 135946,
      "comm_short": 88651,
      "comm_net": 47295,
      "noncomm_long": 60334,
      "noncomm_short": 104501,
      "noncomm_net": -44167,
      "nonrept_net": -3128
    },
    {
      "week": "2024-11-12",
      "open_interest": 257688,
      "comm_long": 153738,
      "comm_short": 81565,
      "comm_net": 72173,
      "noncomm_long": 64038,
      "noncomm_short": 128940,
      "noncomm_net": -64902,
      "nonrept_net": -7271
    },
    {
      "week": "2024-11-19",
      "open_interest": 254087,
      "comm_long": 134065,
      "comm_short": 84856,
      "comm_net": 49209,
      "noncomm_long": 78973,
      "noncomm_short": 125841,
      "noncomm_net": -46868,
      "nonrept_net": -2341
    },
    {
      "week": "2024-11-26",
      "open_interest": 253566,
      "comm_long": 122885,
      "comm_short": 99595,
      "comm_net": 23290,
      "noncomm_long": 87597,
      "noncomm_short": 110230,
      "noncomm_net": -22633,
      "nonrept_net": -657
    },
    {
      "week": "2024-12-03",
      "open_interest": 256849,
      "comm_long": 111171,
      "comm_short": 111335,
      "comm_net": -164,
      "noncomm_long": 93622,
      "noncomm_short": 91288,
      "noncomm_net": 2334,
      "nonrept_net": -2170
    },
    {
      "week": "2024-12-10",
      "open_interest": 274834,
      "comm_long": 117775,
      "comm_short": 142373,
      "comm_net": -24598,
      "noncomm_long": 97938,
      "noncomm_short": 72186,
      "noncomm_net": 25752,
      "nonrept_net": -1154
    },
    {
      "week": "2024-12-17",
      "open_interest": 181673,
      "comm_long": 57107,
      "comm_short": 60208,
      "comm_net": -3101,
      "noncomm_long": 87208,
      "noncomm_short": 81247,
      "noncomm_net": 5961,
      "nonrept_net": -2860
    },
    {
      "week": "2024-12-24",
      "open_interest": 200720,
      "comm_long": 68898,
      "comm_short": 65215,
      "comm_net": 3683,
      "noncomm_long": 95958,
      "noncomm_short": 93647,
      "noncomm_net": 2311,
      "nonrept_net": -5994
    },
    {
      "week": "2024-12-31",
      "open_interest": 206971,
      "comm_long": 71016,
      "comm_short": 61414,
      "comm_net": 9602,
      "noncomm_long": 96119,
      "noncomm_short": 104562,
      "noncomm_net": -8443,
      "nonrept_net": -1159
    },
    {
      "week": "2025-01-07",
      "open_interest": 212456,
      "comm_long": 76577,
      "comm_short": 56293,
      "comm_net": 20284,
      "noncomm_long": 91206,
      "noncomm_short": 111395,
      "noncomm_net": -20189,
      "nonrept_net": -95
    },
    {
      "week": "2025-01-14",
      "open_interest": 223952,
      "comm_long": 88113,
      "comm_short": 57090,
      "comm_net": 31023,
      "noncomm_long": 91434,
      "noncomm_short": 120845,
      "noncomm_net": -29411,
      "nonrept_net": -1612
    },
    {
      "week": "2025-01-21",
      "open_interest": 211620,
      "comm_long": 68868,
      "comm_short": 60039,
      "comm_net": 8829,
      "noncomm_long": 94157,
      "noncomm_short": 108830,
      "noncomm_net": -14673,
      "nonrept_net": 5844
    },
    {
      "week": "2025-01-28",
      "open_interest": 216788,
      "comm_long": 68683,
      "comm_short": 75420,
      "comm_net": -6737,
      "noncomm_long": 96809,
      "noncomm_short": 97768,
      "noncomm_net": -959,
      "nonrept_net": 7696
    },
    {
      "week": "2025-02-04",
      "open_interest": 231911,
      "comm_long": 70418,
      "comm_short": 101101,
      "comm_net": -30683,
      "noncomm_long": 104684,
      "noncomm_short": 85916,
      "noncomm_net": 18768,
      "nonrept_net": 11915
    },
    {
      "week": "2025-02-11",
      "open_interest": 273314,
      "comm_long": 73890,
      "comm_short": 142044,
      "comm_net": -68154,
      "noncomm_long": 144158,
      "noncomm_short": 89543,
      "noncomm_net": 54615,
      "nonrept_net": 13539
    },
    {
      "week": "2025-02-18",
      "open_interest": 281163,
      "comm_long": 84001,
      "comm_short": 154194,
      "comm_net": -70193,
      "noncomm_long": 147566,
      "noncomm_short": 86997,
      "noncomm_net": 60569,
      "nonrept_net": 9624
    },
    {
      "week": "2025-02-25",
      "open_interest": 329186,
      "comm_long": 93060,
      "comm_short": 202005,
      "comm_net": -108945,
      "noncomm_long": 171751,
      "noncomm_short": 75771,
      "noncomm_net": 95980,
      "nonrept_net": 12965
    },
    {
      "week": "2025-03-04",
      "open_interest": 354415,
      "comm_long": 102081,
      "comm_short": 248000,
      "comm_net": -145919,
      "noncomm_long": 183955,
      "noncomm_short": 50304,
      "noncomm_net": 133651,
      "nonrept_net": 12268
    },
    {
      "week": "2025-03-11",
      "open_interest": 446178,
      "comm_long": 178522,
      "comm_short": 327791,
      "comm_net": -149269,
      "noncomm_long": 176790,
      "noncomm_short": 42888,
      "noncomm_net": 133902,
      "nonrept_net": 15367
    },
    {
      "week": "2025-03-18",
      "open_interest": 296567,
      "comm_long": 80456,
      "comm_short": 217232,
      "comm_net": -136776,
      "noncomm_long": 164752,
      "noncomm_short": 41788,
      "noncomm_net": 122964,
      "nonrept_net": 13812
    },
    {
      "week": "2025-03-25",
      "open_interest": 303778,
      "comm_long": 92999,
      "comm_short": 228739,
      "comm_net": -135740,
      "noncomm_long": 160474,
      "noncomm_short": 35098,
      "noncomm_net": 125376,
      "nonrept_net": 10364
    },
    {
      "week": "2025-04-01",
      "open_interest": 311162,
      "comm_long": 96971,
      "comm_short": 235518,
      "comm_net": -138547,
      "noncomm_long": 161566,
      "noncomm_short": 39792,
      "noncomm_net": 121774,
      "nonrept_net": 16773
    },
    {
      "week": "2025-04-08",
      "open_interest": 320758,
      "comm_long": 99659,
      "comm_short": 261328,
      "comm_net": -161669,
      "noncomm_long": 176555,
      "noncomm_short": 29488,
      "noncomm_net": 147067,
      "nonrept_net": 14602
    },
    {
      "week": "2025-04-15",
      "open_interest": 338849,
      "comm_long": 96118,
      "comm_short": 286463,
      "comm_net": -190345,
      "noncomm_long": 198560,
      "noncomm_short": 26705,
      "noncomm_net": 171855,
      "nonrept_net": 18490
    },
    {
      "week": "2025-04-22",
      "open_interest": 351226,
      "comm_long": 100299,
      "comm_short": 301221,
      "comm_net": -200922,
      "noncomm_long": 202373,
      "noncomm_short": 24559,
      "noncomm_net": 177814,
      "nonrept_net": 23108
    },
    {
      "week": "2025-04-29",
      "open_interest": 366246,
      "comm_long": 104910,
      "comm_short": 306807,
      "comm_net": -201897,
      "noncomm_long": 202797,
      "noncomm_short": 23585,
      "noncomm_net": 179212,
      "nonrept_net": 22685
    },
    {
      "week": "2025-05-06",
      "open_interest": 375546,
      "comm_long": 105878,
      "comm_short": 306490,
      "comm_net": -200612,
      "noncomm_long": 204008,
      "noncomm_short": 27149,
      "noncomm_net": 176859,
      "nonrept_net": 23753
    },
    {
      "week": "2025-05-13",
      "open_interest": 359521,
      "comm_long": 101140,
      "comm_short": 286031,
      "comm_net": -184891,
      "noncomm_long": 194226,
      "noncomm_short": 21958,
      "noncomm_net": 172268,
      "nonrept_net": 12623
    },
    {
      "week": "2025-05-20",
      "open_interest": 366865,
      "comm_long": 102102,
      "comm_short": 283123,
      "comm_net": -181021,
      "noncomm_long": 194510,
      "noncomm_short": 27180,
      "noncomm_net": 167330,
      "nonrept_net": 13691
    },
    {
      "week": "2025-05-27",
      "open_interest": 377011,
      "comm_long": 101750,
      "comm_short": 285448,
      "comm_net": -183698,
      "noncomm_long": 191802,
      "noncomm_short": 27790,
      "noncomm_net": 164012,
      "nonrept_net": 19686
    },
    {
      "week": "2025-06-03",
      "open_interest": 366008,
      "comm_long": 100151,
      "comm_short": 275659,
      "comm_net": -175508,
      "noncomm_long": 189514,
      "noncomm_short": 38365,
      "noncomm_net": 151149,
      "nonrept_net": 24359
    },
    {
      "week": "2025-06-10",
      "open_interest": 388263,
      "comm_long": 132044,
      "comm_short": 301121,
      "comm_net": -169077,
      "noncomm_long": 184195,
      "noncomm_short": 39600,
      "noncomm_net": 144595,
      "nonrept_net": 24482
    },
    {
      "week": "2025-06-17",
      "open_interest": 317523,
      "comm_long": 94915,
      "comm_short": 243088,
      "comm_net": -148173,
      "noncomm_long": 175601,
      "noncomm_short": 44724,
      "noncomm_net": 130877,
      "nonrept_net": 17296
    },
    {
      "week": "2025-06-24",
      "open_interest": 314767,
      "comm_long": 92034,
      "comm_short": 239744,
      "comm_net": -147710,
      "noncomm_long": 178403,
      "noncomm_short": 46126,
      "noncomm_net": 132277,
      "nonrept_net": 15433
    },
    {
      "week": "2025-07-01",
      "open_interest": 314251,
      "comm_long": 94864,
      "comm_short": 245721,
      "comm_net": -150857,
      "noncomm_long": 170624,
      "noncomm_short": 43286,
      "noncomm_net": 127338,
      "nonrept_net": 23519
    },
    {
      "week": "2025-07-08",
      "open_interest": 308621,
      "comm_long": 96636,
      "comm_short": 225316,
      "comm_net": -128680,
      "noncomm_long": 166192,
      "noncomm_short": 50037,
      "noncomm_net": 116155,
      "nonrept_net": 12525
    },
    {
      "week": "2025-07-15",
      "open_interest": 321350,
      "comm_long": 108744,
      "comm_short": 219590,
      "comm_net": -110846,
      "noncomm_long": 165444,
      "noncomm_short": 61862,
      "noncomm_net": 103582,
      "nonrept_net": 7264
    },
    {
      "week": "2025-07-22",
      "open_interest": 313040,
      "comm_long": 101532,
      "comm_short": 218892,
      "comm_net": -117360,
      "noncomm_long": 164411,
      "noncomm_short": 57766,
      "noncomm_net": 106645,
      "nonrept_net": 10715
    },
    {
      "week": "2025-07-29",
      "open_interest": 329115,
      "comm_long": 123152,
      "comm_short": 215700,
      "comm_net": -92548,
      "noncomm_long": 162122,
      "noncomm_short": 72879,
      "noncomm_net": 89243,
      "nonrept_net": 3305
    },
    {
      "week": "2025-08-05",
      "open_interest": 337378,
      "comm_long": 136734,
      "comm_short": 224075,
      "comm_net": -87341,
      "noncomm_long": 160258,
      "noncomm_short": 78252,
      "noncomm_net": 82006,
      "nonrept_net": 5335
    },
    {
      "week": "2025-08-12",
      "open_interest": 351163,
      "comm_long": 147170,
      "comm_short": 221065,
      "comm_net": -73895,
      "noncomm_long": 164693,
      "noncomm_short": 90459,
      "noncomm_net": 74234,
      "nonrept_net": -339
    },
    {
      "week": "2025-08-19",
      "open_interest": 348982,
      "comm_long": 139967,
      "comm_short": 219849,
      "comm_net": -79882,
      "noncomm_long": 168363,
      "noncomm_short": 90782,
      "noncomm_net": 77581,
      "nonrept_net": 2301
    },
    {
      "week": "2025-08-26",
      "open_interest": 357366,
      "comm_long": 139358,
      "comm_short": 229508,
      "comm_net": -90150,
      "noncomm_long": 170765,
      "noncomm_short": 86281,
      "noncomm_net": 84484,
      "nonrept_net": 5666
    },
    {
      "week": "2025-09-02",
      "open_interest": 414249,
      "comm_long": 152763,
      "comm_short": 229019,
      "comm_net": -76256,
      "noncomm_long": 174774,
      "noncomm_short": 101516,
      "noncomm_net": 73258,
      "nonrept_net": 2998
    },
    {
      "week": "2025-09-09",
      "open_interest": 410799,
      "comm_long": 157854,
      "comm_short": 258296,
      "comm_net": -100442,
      "noncomm_long": 180724,
      "noncomm_short": 89081,
      "noncomm_net": 91643,
      "nonrept_net": 8799
    },
    {
      "week": "2025-09-16",
      "open_interest": 299620,
      "comm_long": 95157,
      "comm_short": 163495,
      "comm_net": -68338,
      "noncomm_long": 161673,
      "noncomm_short": 100262,
      "noncomm_net": 61411,
      "nonrept_net": 6927
    },
    {
      "week": "2025-09-23",
      "open_interest": 309893,
      "comm_long": 92252,
      "comm_short": 175491,
      "comm_net": -83239,
      "noncomm_long": 176400,
      "noncomm_short": 96900,
      "noncomm_net": 79500,
      "nonrept_net": 3739
    },
    {
      "week": "2025-09-30",
      "open_interest": 305711,
      "comm_long": 96572,
      "comm_short": 157317,
      "comm_net": -60745,
      "noncomm_long": 167811,
      "noncomm_short": 106346,
      "noncomm_net": 61465,
      "nonrept_net": -720
    },
    {
      "week": "2025-10-07",
      "open_interest": 305134,
      "comm_long": 102742,
      "comm_short": 148716,
      "comm_net": -45974,
      "noncomm_long": 159197,
      "noncomm_short": 112890,
      "noncomm_net": 46307,
      "nonrept_net": -333
    },
    {
      "week": "2025-10-14",
      "open_interest": 305003,
      "comm_long": 104332,
      "comm_short": 140952,
      "comm_net": -36620,
      "noncomm_long": 160639,
      "noncomm_short": 123473,
      "noncomm_net": 37166,
      "nonrept_net": -546
    },
    {
      "week": "2025-10-21",
      "open_interest": 307569,
      "comm_long": 92611,
      "comm_short": 160505,
      "comm_net": -67894,
      "noncomm_long": 175724,
      "noncomm_short": 105310,
      "noncomm_net": 70414,
      "nonrept_net": -2520
    },
    {
      "week": "2025-10-28",
      "open_interest": 321889,
      "comm_long": 100864,
      "comm_short": 169477,
      "comm_net": -68613,
      "noncomm_long": 178745,
      "noncomm_short": 110630,
      "noncomm_net": 68115,
      "nonrept_net": 498
    },
    {
      "week": "2025-11-04",
      "open_interest": 314190,
      "comm_long": 100952,
      "comm_short": 148803,
      "comm_net": -47851,
      "noncomm_long": 170180,
      "noncomm_short": 118915,
      "noncomm_net": 51265,
      "nonrept_net": -3414
    },
    {
      "week": "2025-11-10",
      "open_interest": 312845,
      "comm_long": 97752,
      "comm_short": 145775,
      "comm_net": -48023,
      "noncomm_long": 172349,
      "noncomm_short": 123873,
      "noncomm_net": 48476,
      "nonrept_net": -453
    },
    {
      "week": "2025-11-18",
      "open_interest": 329456,
      "comm_long": 114082,
      "comm_short": 144609,
      "comm_net": -30527,
      "noncomm_long": 169890,
      "noncomm_short": 138733,
      "noncomm_net": 31157,
      "nonrept_net": -630
    },
    {
      "week": "2025-11-25",
      "open_interest": 344420,
      "comm_long": 117192,
      "comm_short": 144676,
      "comm_net": -27484,
      "noncomm_long": 169218,
      "noncomm_short": 142701,
      "noncomm_net": 26517,
      "nonrept_net": 967
    },
    {
      "week": "2025-12-02",
      "open_interest": 394859,
      "comm_long": 133444,
      "comm_short": 171567,
      "comm_net": -38123,
      "noncomm_long": 184958,
      "noncomm_short": 148540,
      "noncomm_net": 36418,
      "nonrept_net": 1705
    },
    {
      "week": "2025-12-09",
      "open_interest": 465416,
      "comm_long": 205773,
      "comm_short": 223832,
      "comm_net": -18059,
      "noncomm_long": 184488,
      "noncomm_short": 167040,
      "noncomm_net": 17448,
      "nonrept_net": 611
    },
    {
      "week": "2025-12-16",
      "open_interest": 379679,
      "comm_long": 101002,
      "comm_short": 105746,
      "comm_net": -4744,
      "noncomm_long": 146275,
      "noncomm_short": 149217,
      "noncomm_net": -2942,
      "nonrept_net": 7686
    },
    {
      "week": "2025-12-23",
      "open_interest": 285084,
      "comm_long": 99644,
      "comm_short": 105548,
      "comm_net": -5904,
      "noncomm_long": 141133,
      "noncomm_short": 139910,
      "noncomm_net": 1223,
      "nonrept_net": 4681
    },
    {
      "week": "2025-12-30",
      "open_interest": 286132,
      "comm_long": 95645,
      "comm_short": 114721,
      "comm_net": -19076,
      "noncomm_long": 144596,
      "noncomm_short": 130528,
      "noncomm_net": 14068,
      "nonrept_net": 5008
    },
    {
      "week": "2026-01-06",
      "open_interest": 287715,
      "comm_long": 94001,
      "comm_short": 106169,
      "comm_net": -12168,
      "noncomm_long": 140441,
      "noncomm_short": 131626,
      "noncomm_net": 8815,
      "nonrept_net": 3353
    },
    {
      "week": "2026-01-13",
      "open_interest": 294242,
      "comm_long": 114303,
      "comm_short": 68484,
      "comm_net": 45819,
      "noncomm_long": 111743,
      "noncomm_short": 156907,
      "noncomm_net": -45164,
      "nonrept_net": -655
    },
    {
      "week": "2026-01-20",
      "open_interest": 292607,
      "comm_long": 115583,
      "comm_short": 74443,
      "comm_net": 41140,
      "noncomm_long": 107139,
      "noncomm_short": 151968,
      "noncomm_net": -44829,
      "nonrept_net": 3689
    },
    {
      "week": "2026-01-27",
      "open_interest": 300726,
      "comm_long": 125157,
      "comm_short": 98448,
      "comm_net": 26709,
      "noncomm_long": 104460,
      "noncomm_short": 138393,
      "noncomm_net": -33933,
      "nonrept_net": 7224
    },
    {
      "week": "2026-02-03",
      "open_interest": 303673,
      "comm_long": 122665,
      "comm_short": 108248,
      "comm_net": 14417,
      "noncomm_long": 114428,
      "noncomm_short": 133650,
      "noncomm_net": -19222,
      "nonrept_net": 4805
    },
    {
      "week": "2026-02-10",
      "open_interest": 334948,
      "comm_long": 136055,
      "comm_short": 123376,
      "comm_net": 12679,
      "noncomm_long": 128090,
      "noncomm_short": 147196,
      "noncomm_net": -19106,
      "nonrept_net": 6427
    },
    {
      "week": "2026-02-17",
      "open_interest": 354328,
      "comm_long": 141766,
      "comm_short": 157934,
      "comm_net": -16168,
      "noncomm_long": 143172,
      "noncomm_short": 130217,
      "noncomm_net": 12955,
      "nonrept_net": 3213
    },
    {
      "week": "2026-02-24",
      "open_interest": 369721,
      "comm_long": 141918,
      "comm_short": 156647,
      "comm_net": -14729,
      "noncomm_long": 149364,
      "noncomm_short": 137825,
      "noncomm_net": 11539,
      "nonrept_net": 3190
    },
    {
      "week": "2026-03-03",
      "open_interest": 416977,
      "comm_long": 186027,
      "comm_short": 171020,
      "comm_net": 15007,
      "noncomm_long": 134945,
      "noncomm_short": 151520,
      "noncomm_net": -16575,
      "nonrept_net": 1568
    },
    {
      "week": "2026-03-10",
      "open_interest": 427718,
      "comm_long": 220577,
      "comm_short": 174607,
      "comm_net": 45970,
      "noncomm_long": 119411,
      "noncomm_short": 160798,
      "noncomm_net": -41387,
      "nonrept_net": -4583
    },
    {
      "week": "2026-03-17",
      "open_interest": 326688,
      "comm_long": 163975,
      "comm_short": 93973,
      "comm_net": 70002,
      "noncomm_long": 106819,
      "noncomm_short": 174599,
      "noncomm_net": -67780,
      "nonrept_net": -2222
    },
    {
      "week": "2026-03-24",
      "open_interest": 328210,
      "comm_long": 167443,
      "comm_short": 109542,
      "comm_net": 57901,
      "noncomm_long": 98271,
      "noncomm_short": 161077,
      "noncomm_net": -62806,
      "nonrept_net": 4905
    },
    {
      "week": "2026-03-31",
      "open_interest": 345276,
      "comm_long": 185944,
      "comm_short": 115237,
      "comm_net": 70707,
      "noncomm_long": 95356,
      "noncomm_short": 168228,
      "noncomm_net": -72872,
      "nonrept_net": 2165
    },
    {
      "week": "2026-04-07",
      "open_interest": 349373,
      "comm_long": 192103,
      "comm_short": 101707,
      "comm_net": 90396,
      "noncomm_long": 91560,
      "noncomm_short": 185302,
      "noncomm_net": -93742,
      "nonrept_net": 3346
    },
    {
      "week": "2026-04-14",
      "open_interest": 354344,
      "comm_long": 187189,
      "comm_short": 106141,
      "comm_net": 81048,
      "noncomm_long": 102114,
      "noncomm_short": 185322,
      "noncomm_net": -83208,
      "nonrept_net": 2160
    },
    {
      "week": "2026-04-21",
      "open_interest": 351782,
      "comm_long": 188723,
      "comm_short": 93256,
      "comm_net": 95467,
      "noncomm_long": 101386,
      "noncomm_short": 195846,
      "noncomm_net": -94460,
      "nonrept_net": -1007
    },
    {
      "week": "2026-04-28",
      "open_interest": 372780,
      "comm_long": 201527,
      "comm_short": 102257,
      "comm_net": 99270,
      "noncomm_long": 106530,
      "noncomm_short": 208589,
      "noncomm_net": -102059,
      "nonrept_net": 2789
    },
    {
      "week": "2026-05-05",
      "open_interest": 354005,
      "comm_long": 186544,
      "comm_short": 126894,
      "comm_net": 59650,
      "noncomm_long": 109035,
      "noncomm_short": 170773,
      "noncomm_net": -61738,
      "nonrept_net": 2088
    },
    {
      "week": "2026-05-12",
      "open_interest": 362042,
      "comm_long": 203023,
      "comm_short": 128880,
      "comm_net": 74143,
      "noncomm_long": 100155,
      "noncomm_short": 175257,
      "noncomm_net": -75102,
      "nonrept_net": 959
    }
  ],
  "data_computed": "2026-05-29T22:30:08Z"
}